fare/__init__.py
fare/audit.py
fare/metrics.py
fare-0.1.1.dist-info/LICENSE
fare-0.1.1.dist-info/METADATA
fare-0.1.1.dist-info/WHEEL
fare-0.1.1.dist-info/top_level.txt
fare-0.1.1.dist-info/RECORD
