Metadata-Version: 2.1
Name: fare
Version: 0.1.1
Summary: Fare auditing diagnostics and pairwise fairness error metrics for ranking.
Home-page: https://github.com/caitlinkuhlman/fare
Maintainer: Caitlin Kuhlman
Maintainer-email: cakuhlman@wpi.edu
License: new BSD
Download-URL: https://github.com/caitlinkuhlman/fare
Platform: UNKNOWN
Classifier: Intended Audience :: Science/Research
Classifier: Intended Audience :: Developers
Classifier: License :: OSI Approved
Classifier: Programming Language :: Python
Classifier: Topic :: Software Development
Classifier: Topic :: Scientific/Engineering
Classifier: Operating System :: Microsoft :: Windows
Classifier: Operating System :: POSIX
Classifier: Operating System :: Unix
Classifier: Operating System :: MacOS
Classifier: Programming Language :: Python :: 2.7
Classifier: Programming Language :: Python :: 3.5
Classifier: Programming Language :: Python :: 3.6
Classifier: Programming Language :: Python :: 3.7
Requires-Dist: numpy
Requires-Dist: scipy
Requires-Dist: matplotlib
